lib/arrow-core_2.13.jar
lib/arrow-messaging_2.13.jar
lib/core_2.13.jar
pyraphtory/__init__.py
pyraphtory/_codegen.py
pyraphtory/_config.py
pyraphtory/_docstring.py
pyraphtory/_jpypeinterpreter.py
pyraphtory/_py4jgateway.py
pyraphtory/algorithm.py
pyraphtory/algorithms/__init__.py
pyraphtory/algorithms/connectedcomponents.py
pyraphtory/algorithms/degree.py
pyraphtory/algorithms/pagerank.py
pyraphtory/algorithms/sample.py
pyraphtory/algorithms/trianglecount.py
pyraphtory/algorithms/twohoppaths.py
pyraphtory/cli.py
pyraphtory/context.py
pyraphtory/debug.py
pyraphtory/formats.py
pyraphtory/graph.py
pyraphtory/input.py
pyraphtory/interop.py
pyraphtory/scala/__init__.py
pyraphtory/scala/collection.py
pyraphtory/scala/implicits/__init__.py
pyraphtory/scala/implicits/bounded.py
pyraphtory/scala/implicits/numeric.py
pyraphtory/scala/implicits/schemas.py
pyraphtory/sinks.py
pyraphtory/sources.py
pyraphtory/spouts.py
pyraphtory/vertex.py
pyraphtory-0.1.4.dist-info/entry_points.txt
pyraphtory-0.1.4.dist-info/METADATA
pyraphtory-0.1.4.dist-info/LICENSE
pyraphtory-0.1.4.dist-info/WHEEL
pyraphtory-0.1.4.dist-info/RECORD
